[
    {
        "id": 1,
        "guid": "9f507483-5ecc-4af4-800f-349306820585",
        "isActive": false,
        "balance": "$2,407.00",
        "picture": "http://placehold.it/32x32",
        "age": 22,
        "name": "Champ A",
        "gender": "Champ B",
        "company": "Champ C",
        "email": "Champ 4",
        "phone": "Modif1",
        "address": {
            "street": 155,
            "city": "Cherokee",
            "state": "Kentucky",
            "zip": 4723
        },
        "about": "Indicateur1",
        "registered": "Modif2",
        "friends": [
            {
                "id": 0,
                "name": "Brewer Maxwell"
            },
            {
                "id": 1,
                "name": "Ayala Franks"
            },
            {
                "id": 2,
                "name": "Hale Nichols"
            }
        ]
    },
    {
        "id": 2,
        "guid": "9f507483-5ecc-4af4-800f-349306820585",
        "isActive": false,
        "balance": "$2,407.00",
        "picture": "http://placehold.it/32x32",
        "age": 22,
        "name": "Champ A",
        "gender": "Champ B",
        "company": "Champ C",
        "email": "Champ 4",
        "phone": "Modif1",
        "address": {
            "street": 155,
            "city": "Cherokee",
            "state": "Kentucky",
            "zip": 4723
        },
        "about": "Indicateur1",
        "registered": "Modif2",
        "friends": [
            {
                "id": 0,
                "name": "Brewer Maxwell"
            },
            {
                "id": 1,
                "name": "Ayala Franks"
            },
            {
                "id": 2,
                "name": "Hale Nichols"
            }
        ]
    },
    {
        "id": 3,
        "guid": "9f507483-5ecc-4af4-800f-349306820585",
        "isActive": false,
        "balance": "$2,407.00",
        "picture": "http://placehold.it/32x32",
        "age": 22,
        "name": "Champ A",
        "gender": "Champ B",
        "company": "Champ C",
        "email": "Champ 4",
        "phone": "Modif1",
        "address": {
            "street": 155,
            "city": "Cherokee",
            "state": "Kentucky",
            "zip": 4723
        },
        "about": "Indicateur1",
        "registered": "Modif2",
        "friends": [
            {
                "id": 0,
                "name": "Brewer Maxwell"
            },
            {
                "id": 1,
                "name": "Ayala Franks"
            },
            {
                "id": 2,
                "name": "Hale Nichols"
            }
        ]
    },
    {
        "id": 4,
        "guid": "9f507483-5ecc-4af4-800f-349306820585",
        "isActive": false,
        "balance": "$2,407.00",
        "picture": "http://placehold.it/32x32",
        "age": 22,
        "name": "Champ A",
        "gender": "Champ B",
        "company": "Champ C",
        "email": "Champ 4",
        "phone": "Modif1",
        "address": {
            "street": 155,
            "city": "Cherokee",
            "state": "Kentucky",
            "zip": 4723
        },
        "about": "Indicateur1",
        "registered": "Modif2",
        "friends": [
            {
                "id": 0,
                "name": "Brewer Maxwell"
            },
            {
                "id": 1,
                "name": "Ayala Franks"
            },
            {
                "id": 2,
                "name": "Hale Nichols"
            }
        ]
    },
    {
        "id": 5,
        "guid": "9f507483-5ecc-4af4-800f-349306820585",
        "isActive": false,
        "balance": "$2,407.00",
        "picture": "http://placehold.it/32x32",
        "age": 22,
        "name": "Champ A",
        "gender": "Champ B",
        "company": "Champ C",
        "email": "Champ 4",
        "phone": "Modif1",
        "address": {
            "street": 155,
            "city": "Cherokee",
            "state": "Kentucky",
            "zip": 4723
        },
        "about": "Indicateur1",
        "registered": "Modif2",
        "friends": [
            {
                "id": 0,
                "name": "Brewer Maxwell"
            },
            {
                "id": 1,
                "name": "Ayala Franks"
            },
            {
                "id": 2,
                "name": "Hale Nichols"
            }
        ]
    },
    {
        "id": 6,
        "guid": "9f507483-5ecc-4af4-800f-349306820585",
        "isActive": false,
        "balance": "$2,407.00",
        "picture": "http://placehold.it/32x32",
        "age": 22,
        "name": "Champ A",
        "gender": "Champ B",
        "company": "Champ C",
        "email": "Champ 4",
        "phone": "Modif1",
        "address": {
            "street": 155,
            "city": "Cherokee",
            "state": "Kentucky",
            "zip": 4723
        },
        "about": "Indicateur1",
        "registered": "Modif2",
        "friends": [
            {
                "id": 0,
                "name": "Brewer Maxwell"
            },
            {
                "id": 1,
                "name": "Ayala Franks"
            },
            {
                "id": 2,
                "name": "Hale Nichols"
            }
        ]
    },
    {
        "id": 7,
        "guid": "9f507483-5ecc-4af4-800f-349306820585",
        "isActive": false,
        "balance": "$2,407.00",
        "picture": "http://placehold.it/32x32",
        "age": 22,
        "name": "Champ A",
        "gender": "Champ B",
        "company": "Champ C",
        "email": "Champ 4",
        "phone": "Modif1",
        "address": {
            "street": 155,
            "city": "Cherokee",
            "state": "Kentucky",
            "zip": 4723
        },
        "about": "Indicateur1",
        "registered": "Modif2",
        "friends": [
            {
                "id": 0,
                "name": "Brewer Maxwell"
            },
            {
                "id": 1,
                "name": "Ayala Franks"
            },
            {
                "id": 2,
                "name": "Hale Nichols"
            }
        ]
    }

]